README.md
setup.py
linkalman/__init__.py
linkalman.egg-info/PKG-INFO
linkalman.egg-info/SOURCES.txt
linkalman.egg-info/dependency_links.txt
linkalman.egg-info/requires.txt
linkalman.egg-info/top_level.txt
linkalman/core/__init__.py
linkalman/core/kalman_filter.py
linkalman/core/kalman_smoother.py
linkalman/core/utils.py
linkalman/models/__init__.py
linkalman/models/base.py