Metadata-Version: 2.1
Name: linkalman
Version: 0.11.5
Summary: Flexible Linear Kalman Filter
Home-page: https://github.com/DanyangSu/linkalman
Author: Danyang Su
Author-email: fnosdy@gmail.com
License: 3-clause BSD
Download-URL: https://github.com/DanyangSu/linkalman/archive/v0.11.2.tar.gz
Keywords: kalman,time series,signal,filter
Platform: UNKNOWN
Classifier: Development Status :: 3 - Alpha
Classifier: Intended Audience :: Science/Research
Classifier: License :: OSI Approved :: BSD License
Classifier: Operating System :: OS Independent
Classifier: Programming Language :: Python :: 3
Classifier: Topic :: Scientific/Engineering :: Artificial Intelligence
